regulus/__init__.py
regulus/_version.py
regulus/command_line.py
regulus/alg/__init__.py
regulus/alg/alg.py
regulus/core/__init__.py
regulus/core/cache.py
regulus/core/data.py
regulus/core/hasattrs.py
regulus/core/hastree.py
regulus/data/__init__.py
regulus/data/data.py
regulus/errors/__init__.py
regulus/errors/error.py
regulus/measures/__init__.py
regulus/measures/linear.py
regulus/measures/node.py
regulus/measures/quadratic.py
regulus/models/__init__.py
regulus/models/inv_reg.py
regulus/models/linear_model.py
regulus/models/null_model.py
regulus/models/quadratic_model.py
regulus/topo/__init__.py
regulus/topo/alg.py
regulus/topo/builder.py
regulus/topo/hasattrs.py
regulus/topo/morse.py
regulus/topo/regulus.py
regulus/tree/__init__.py
regulus/tree/alg.py
regulus/tree/apply.py
regulus/tree/hastree.py
regulus/tree/traverse.py
regulus/tree/tree.py
regulus/utils/__init__.py
regulus/utils/cache.py
regulus/utils/io.py
regulus/utils/timed.py
regulus-0.8.0.dist-info/LICENSE
regulus-0.8.0.dist-info/METADATA
regulus-0.8.0.dist-info/WHEEL
regulus-0.8.0.dist-info/entry_points.txt
regulus-0.8.0.dist-info/top_level.txt
regulus-0.8.0.dist-info/RECORD
