Metadata-Version: 2.1
Name: regulus
Version: 0.8.0
Summary: Regulus
Home-page: https://github.com/yarden_livnat/regulus
Author: Yarden Livnat
Author-email: yarden@sci.utah.edu
License: BSD 3-Clause License
Requires-Dist: topopy (>=0.1)
Requires-Dist: numpy
Requires-Dist: sklearn
Requires-Dist: pandas
